README.md
setup.cfg
setup.py
roman_nums/__init__.py
roman_nums/errors.py
roman_nums/tests.py
roman_nums/utils.py
roman_nums.egg-info/PKG-INFO
roman_nums.egg-info/SOURCES.txt
roman_nums.egg-info/dependency_links.txt
roman_nums.egg-info/top_level.txt