Metadata-Version: 2.1
Name: roman-nums
Version: 0.0.1
Summary: UNKNOWN
Home-page: https://github.com/kovalenkong/roman-nums
Author: Kovalenko Nikolay
Author-email: kovalenko.n.r-g@yandex.ru
License: UNKNOWN
Platform: UNKNOWN
Requires-Python: >=3.6
